{
    "qCardinal": {
        "desc": "Cardinality of the attribute expression. ",
        "class": "Int",
        "type": "primitive"
    },
    "qSize": {
        "desc": "Number of rows.",
        "class": "Size",
        "type": "primitive"
    },
    "qFallbackTitle": {
        "desc": "The title for the attribute dimension.",
        "class": "String",
        "type": "primitive"
    },
    "qLocked": {
        "desc": "The Locked value of the dimension.",
        "class": "Boolean",
        "type": "primitive"
    },
    "qError": {
        "desc": "Validation error.",
        "class": "REF(NxValidationError)",
        "type": "primitive"
    }
}